mypyy-0.0.1.dist-info/licenses/LICENSE
py/__init__.py
mypyy-0.0.1.dist-info/METADATA
mypyy-0.0.1.dist-info/WHEEL
mypyy-0.0.1.dist-info/top_level.txt
mypyy-0.0.1.dist-info/RECORD
